{
  "bookCode": "JOB",
  "chapter": 34,
  "verses": [
    {
      "verse": 1,
      "texts": {
        "BDS": "Elihou poursuivit son discours:",
        "DBY": "Et Élihu reprit la parole et dit:",
        "KJV": "Furthermore Elihu answered and said,",
        "LSG": "Elihu reprit et dit:",
        "MAB": "Elihu donc reprit la parole, et dit :",
        "OST": "Élihu reprit la parole, et dit:",
        "S21": "Elihu reprit:"
      }
    },
    {
      "verse": 2,
      "texts": {
        "BDS": "O vous qui êtes sages, écoutez mes paroles,\r\net vous, gens de science, prêtez votre attention!",
        "DBY": "Sages, écoutez mes paroles, et vous qui avez de la connaissance, prêtez-moi l'oreille;",
        "KJV": "Hear my words, O ye wise [men]; and give ear unto me, ye that have knowledge.",
        "LSG": "Sages, écoutez mes discours! Vous qui êtes intelligents, prêtez-moi l'oreille!",
        "MAB": "Vous sages écoutez mes discours, et vous qui avez de l'intelligence, prêtez-moi l'oreille.",
        "OST": "Vous, sages, écoutez mes discours; et vous, savants, prêtez-moi l'oreille.",
        "S21": "«Sages, écoutez mes propos! Vous qui êtes des connaisseurs, prêtez l'oreille à ce que je vais dire!"
      }
    },
    {
      "verse": 3,
      "texts": {
        "BDS": "Car l’oreille discerne la valeur des paroles,\r\ncomme le palais juge du goût des aliments.",
        "DBY": "Car l'oreille éprouve les discours, comme le palais goûte les aliments.",
        "KJV": "For the ear trieth words, as the mouth tasteth meat.",
        "LSG": "Car l'oreille discerne les paroles, Comme le palais savoure les aliments.",
        "MAB": "Car l'oreille juge des discours, ainsi que le palais savoure ce que l'on mange.",
        "OST": "Car l'oreille juge des discours, comme le palais goûte ce qu'on doit manger.",
        "S21": "En effet, l'oreille jauge les propos tout comme le palais goûte les aliments."
      }
    },
    {
      "verse": 4,
      "texts": {
        "BDS": "Examinons ensemble, pour nous, ce qui est juste.\r\nEt cherchons entre nous ce qui est bien.",
        "DBY": "Choisissons pour nous ce qui est juste, et reconnaissons entre nous ce qui est bon.",
        "KJV": "Let us choose to us judgment: let us know among ourselves what [is] good.",
        "LSG": "Choisissons ce qui est juste, Voyons entre nous ce qui est bon.",
        "MAB": "Choisissons [de quoi nous devons disputer comme en] jugement, [puis] nous connaîtrons entre nous ce qui est bon.",
        "OST": "Choisissons ensemble ce qui est juste; voyons, entre nous, ce qui est bon.",
        "S21": "Choisissons pour nous ce qui est juste, sachons reconnaître entre nous ce qui est bon!"
      }
    },
    {
      "verse": 5,
      "texts": {
        "BDS": "Voici ce qu’a prétendu Job: «Je suis dans mon bon droit,\r\nmais Dieu me refuse justice.",
        "DBY": "Car Job a dit: Je suis juste, et Dieu a écarté mon droit;",
        "KJV": "For Job hath said, I am righteous: and God hath taken away my judgment.",
        "LSG": "Job dit: Je suis innocent, Et Dieu me refuse justice;",
        "MAB": "Car Job a dit : Je suis juste, et cependant le [Dieu] Fort a mis mon droit à l'écart.",
        "OST": "Job a dit: \"Je suis juste, mais Dieu met mon droit de côté;",
        "S21": "»Job dit en effet: ‘Je suis juste et Dieu me refuse justice."
      }
    },
    {
      "verse": 6,
      "texts": {
        "BDS": "Alors que je suis juste je passe pour menteur.\r\nJe suis percé de flèches sans avoir commis de péché.»",
        "DBY": "Mentirai-je contre ma droiture? ma blessure est incurable, sans qu'il y ait de transgression.",
        "KJV": "Should I lie against my right? my wound [is] incurable without transgression.",
        "LSG": "J'ai raison, et je passe pour menteur; Ma plaie est douloureuse, et je suis sans péché.",
        "MAB": "Mentirais-je à mon droit? ma flèche est mortelle, sans que j'aie commis de crime.",
        "OST": "En dépit de mon droit, je suis un menteur; ma plaie est douloureuse, sans que j'aie péché. \"",
        "S21": "Alors que j'ai raison, je passe pour un menteur. Ma blessure est incurable alors que je n’ai pas commis de transgression.’"
      }
    },
    {
      "verse": 7,
      "texts": {
        "BDS": "Quel homme est comme Job,\r\npour boire l’insolence comme on boirait de l’eau?",
        "DBY": "Qui est l'homme qui soit comme Job? Il boit la moquerie comme l'eau;",
        "KJV": "What man [is] like Job, [who] drinketh up scorning like water?",
        "LSG": "Y a-t-il un homme semblable à Job, Buvant la raillerie comme l'eau,",
        "MAB": "[Mais] où y a-t-il un homme comme Job qui avale la moquerie comme de l'eau?",
        "OST": "Y a-t-il un homme tel que Job, qui boit le blasphème comme l'eau,",
        "S21": "»Y a-t-il un homme tel que Job, qui boive l’insolence comme l'eau,"
      }
    },
    {
      "verse": 8,
      "texts": {
        "BDS": "Il fait cause commune avec les malfaiteurs\r\net marche en compagnie de ceux qui sont méchants.",
        "DBY": "Il marche dans la compagnie des ouvriers d'iniquité, et il chemine avec les hommes méchants.",
        "KJV": "Which goeth in company with the workers of iniquity, and walketh with wicked men.",
        "LSG": "Marchant en société de ceux qui font le mal, Cheminant de pair avec les impies?",
        "MAB": "Qui marche en la compagnie des ouvriers d'iniquité, et qui fréquente les méchants?",
        "OST": "Qui marche dans la compagnie des ouvriers d'iniquité, et qui va avec les hommes pervers?",
        "S21": "qui marche en compagnie de ceux qui commettent l’injustice, qui fasse route avec les hommes méchants?"
      }
    },
    {
      "verse": 9,
      "texts": {
        "BDS": "N’a-t-il pas dit lui-même: «L’homme ne gagne rien\r\nà vouloir plaire à Dieu»?",
        "DBY": "Car il a dit: Il ne profite de rien à l'homme de trouver son plaisir en Dieu.",
        "KJV": "For he hath said, It profiteth a man nothing that he should delight himself with God.",
        "LSG": "Car il a dit: Il est inutile à l'homme De mettre son plaisir en Dieu.",
        "MAB": "Car [Job] a dit, il ne sert de rien à l'homme de se plaire avec Dieu.",
        "OST": "Car il a dit: L'homme ne gagne rien à se plaire avec Dieu.",
        "S21": "En effet, il a dit: ‘L'homme ne gagne rien à mettre son plaisir en Dieu.’"
      }
    },
    {
      "verse": 10,
      "texts": {
        "BDS": "Aussi, écoutez-moi, vous qui êtes sensés:\r\nil est inconcevable que Dieu fasse le mal,\r\net que le Tout-Puissant pratique l’injustice,",
        "DBY": "C'est pourquoi, hommes de sens, écoutez-moi: Loin de Dieu la méchanceté, et loin du Tout-puissant l'iniquité!",
        "KJV": "Therefore hearken unto me, ye men of understanding: far be it from God, [that he should do] wickedness; and [from] the Almighty, [that he should commit] iniquity.",
        "LSG": "Ecoutez-moi donc, hommes de sens! Loin de Dieu l'injustice, Loin du Tout-Puissant l'iniquité!",
        "MAB": "C'est pourquoi vous qui avez de l'intelligence écoutez-moi. A Dieu ne plaise qu'il y ait de la méchanceté dans le [Dieu] Fort, et de l'injustice dans le Tout-puissant!",
        "OST": "C'est pourquoi, vous qui avez de l'intelligence, écoutez-moi. Loin de Dieu la méchanceté! loin du Tout-Puissant l'injustice!",
        "S21": "»Ecoutez-moi donc, hommes de bon sens! Dieu n’a rien à voir avec la méchanceté, le Tout-Puissant n’a rien à voir avec l’injustice."
      }
    },
    {
      "verse": 11,
      "texts": {
        "BDS": "car il rend à chaque homme selon ce qu’il a fait,\r\net il traite chacun selon son attitude.",
        "DBY": "Car il rendra à l'homme ce qu'il aura fait, et il fera trouver à chacun selon sa voie.",
        "KJV": "For the work of a man shall he render unto him, and cause every man to find according to [his] ways.",
        "LSG": "Il rend à l'homme selon ses oeuvres, Il rétribue chacun selon ses voies.",
        "MAB": "Car il rendra à l'homme selon son œuvre, et il fera trouver à chacun selon sa voie.",
        "OST": "Il rend à l'homme selon ses œuvres, et il fait trouver à chacun selon sa conduite.",
        "S21": "Il paie à l'homme le salaire de ses actes, il traite chacun en fonction de sa conduite."
      }
    },
    {
      "verse": 12,
      "texts": {
        "BDS": "Oh, non en vérité, Dieu n’agit jamais mal,\r\njamais le Tout-Puissant ne fausse la justice.",
        "DBY": "Certainement Dieu n'agit pas injustement, et le Tout-puissant ne pervertit pas le droit.",
        "KJV": "Yea, surely God will not do wickedly, neither will the Almighty pervert judgment.",
        "LSG": "Non certes, Dieu ne commet pas l'iniquité; Le Tout-Puissant ne viole pas la justice.",
        "MAB": "Certainement, le [Dieu] Fort ne déclare point méchant [l'homme de bien], et le Tout-puissant ne renverse point le droit.",
        "OST": "Certainement Dieu ne commet pas d'injustice, le Tout-Puissant ne fait pas fléchir le droit.",
        "S21": "En vérité, Dieu ne commet pas le mal, le Tout-Puissant ne fausse pas le droit."
      }
    },
    {
      "verse": 13,
      "texts": {
        "BDS": "Qui donc l’a établi gouverneur de la terre\r\nou qui lui a remis le soin du monde entier?",
        "DBY": "Qui a confié la terre à ses soins, et qui a placé le monde entier sous lui?",
        "KJV": "Who hath given him a charge over the earth? or who hath disposed the whole world?",
        "LSG": "Qui l'a chargé de gouverner la terre? Qui a confié l'univers à ses soins?",
        "MAB": "Qui est-ce qui lui a donné la terre en charge ? ou qui est-ce qui a placé la terre habitable toute entière?",
        "OST": "Qui lui a commis le soin de la terre? Qui lui a confié l'univers?",
        "S21": "»Qui l'a chargé de gouverner la terre? Qui a confié le monde entier à ses soins?"
      }
    },
    {
      "verse": 14,
      "texts": {
        "BDS": "Oui, s’il portait sur lui toute son attention,\r\ns’il ramenait à lui son Esprit et son souffle,",
        "DBY": "S'il ne pensait qu'à lui-même et retirait à lui son esprit et son souffle,",
        "KJV": "If he set his heart upon man, [if] he gather unto himself his spirit and his breath;",
        "LSG": "S'il ne pensait qu'à lui-même, S'il retirait à lui son esprit et son souffle,",
        "MAB": "Si [Dieu] prenait garde à lui de près, il retirerait à soi son esprit et son souffle.",
        "OST": "S'il ne pensait qu'à lui, s'il retirait à lui son esprit et son souffle,",
        "S21": "S'il ne pensait qu'à lui-même, s'il reprenait son esprit et son souffle,"
      }
    },
    {
      "verse": 15,
      "texts": {
        "BDS": "toutes les créatures expireraient ensemble;\r\nl’homme retournerait aussi à la poussière.",
        "DBY": "Toute chair expirerait ensemble et l'homme retournerait à la poussière.",
        "KJV": "All flesh shall perish together, and man shall turn again unto dust.",
        "LSG": "Toute chair périrait soudain, Et l'homme rentrerait dans la poussière.",
        "MAB": "Toute chair expirerait ensemble, et l'homme retournerait dans la poudre.",
        "OST": "Toute chair expirerait à la fois, et l'homme retournerait dans la poussière.",
        "S21": "toute créature expirerait d’un seul coup et l'homme retournerait à la poussière."
      }
    },
    {
      "verse": 16,
      "texts": {
        "BDS": "Si tu as du bon sens, écoute donc ceci,\r\net sois bien attentif à mes paroles.",
        "DBY": "Si tu as de l'intelligence, écoute ceci; prête l'oreille à la voix de mes paroles.",
        "KJV": "If now [thou hast] understanding, hear this: hearken to the voice of my words.",
        "LSG": "Si tu as de l'intelligence, écoute ceci, Prête l'oreille au son de mes paroles!",
        "MAB": "Si donc tu as de l'intelligence, écoute ceci, prête l'oreille à ce que tu entendras de moi.",
        "OST": "Si donc tu as de l'intelligence, écoute cela; prête l'oreille au son de mes paroles.",
        "S21": "»Si tu as de l'intelligence, écoute ceci, prête l'oreille au son de mes paroles!"
      }
    },
    {
      "verse": 17,
      "texts": {
        "BDS": "Un ennemi du droit pourrait-il gouverner?\r\nOses-tu condamner le Juste, le Puissant?",
        "DBY": "Celui qui hait la justice gouvernera-t-il donc? Et condamneras-tu le juste par excellence?",
        "KJV": "Shall even he that hateth right govern? and wilt thou condemn him that is most just?",
        "LSG": "Un ennemi de la justice régnerait-il? Et condamneras-tu le juste, le puissant,",
        "MAB": "Comment celui qui n'aimerait pas à faire justice, jugerait-il le monde? et condamneras-tu comme méchant celui qui est souverainement juste?",
        "OST": "Eh quoi! celui qui haïrait la justice, régnerait-il? Et condamnerais-tu celui qui est souverainement juste?",
        "S21": "Celui qui déteste le droit pourrait-il vraiment régner? Condamnerais-tu le juste, le puissant?"
      }
    },
    {
      "verse": 18,
      "texts": {
        "BDS": "Celui qui dit aux rois: «Tu n’es qu’un scélérat»,\r\net qui traite les grands de criminels,",
        "DBY": "Dira-t-on Bélial, au roi? -Méchants, aux nobles?",
        "KJV": "[Is it fit] to say to a king, [Thou art] wicked? [and] to princes, [Ye are] ungodly?",
        "LSG": "Qui proclame la méchanceté des rois Et l'iniquité des princes,",
        "MAB": "Dira-t-on à un Roi, qu'il est un scélérat? et aux Princes, qu'ils sont des méchants?",
        "OST": "Lui qui dit aux rois \"Scélérat! \" et \"Méchant! \" aux princes;",
        "S21": "Dit-on aux rois: ‘Vous êtes des vauriens’ et aux princes: ‘Vous êtes des crapules’?"
      }
    },
    {
      "verse": 19,
      "texts": {
        "BDS": "ne favorise pas les princes,\r\net ne fait pas passer le riche avant le pauvre.\r\nIls sont, en effet, tous les deux l’ouvrage de ses mains.",
        "DBY": "Combien moins à celui qui ne fait pas acception de la personne des princes, et qui n'a pas égard au riche plutôt qu'au pauvre; car ils sont tous l'œuvre de ses mains.",
        "KJV": "[How much less to him] that accepteth not the persons of princes, nor regardeth the rich more than the poor? for they all [are] the work of his hands.",
        "LSG": "Qui n'a point égard à l'apparence des grands Et ne distingue pas le riche du pauvre, Parce que tous sont l'ouvrage de ses mains?",
        "MAB": "[Combien moins le dira-t-on à celui] qui n'a point d'égard à la personne des grands, et [qui] ne connaît point les riches pour les préférer aux pauvres, parce qu'ils sont tous l'ouvrage de ses mains.",
        "OST": "Qui n'a point égard à la personne des grands, qui ne connaît pas le riche plus que le pauvre, car ils sont tous l'ouvrage de ses mains?",
        "S21": "Lui, il ne favorise pas les chefs et ne privilégie pas le riche face au pauvre, parce que tous sont l'œuvre de ses mains."
      }
    },
    {
      "verse": 20,
      "texts": {
        "BDS": "En un instant, ils meurent:\r\nau milieu de la nuit, un peuple se révolte, alors ils disparaissent;\r\non dépose un tyran sans qu’une main se lève,",
        "DBY": "Ils mourront en un moment; au milieu de la nuit les peuples chancellent et s'en vont, et les puissants sont retirés sans main.",
        "KJV": "In a moment shall they die, and the people shall be troubled at midnight, and pass away: and the mighty shall be taken away without hand.",
        "LSG": "En un instant, ils perdent la vie; Au milieu de la nuit, un peuple chancelle et périt; Le puissant disparaît, sans la main d'aucun homme.",
        "MAB": "Ils mourront en un moment, et à minuit tout un peuple sera rempli de frayeur et passera; et le fort sera emporté sans qu'aucune main le frappe.",
        "OST": "En un moment ils mourront; au milieu de la nuit, un peuple est ébranlé et passe; le potentat puissant est emporté, et non par une main d'homme.",
        "S21": "En un instant, ils meurent. Au milieu de la nuit, un peuple est ébranlé et disparaît, le tyran est écarté sans aucune intervention humaine."
      }
    },
    {
      "verse": 21,
      "texts": {
        "BDS": "car Dieu observe la conduite de l’homme,\r\net il a les regards sur tous ses faits et gestes.",
        "DBY": "Car ses yeux sont sur les voies de l'homme, et il voit tous ses pas.",
        "KJV": "For his eyes [are] upon the ways of man, and he seeth all his goings.",
        "LSG": "Car Dieu voit la conduite de tous, Il a les regards sur les pas de chacun.",
        "MAB": "Car ses yeux sont sur les voies de chacun, et il regarde tous leurs pas.",
        "OST": "Car les yeux de Dieu sont sur les voies de l'homme, et il regarde tous ses pas.",
        "S21": "»En effet, Dieu est attentif à la conduite de l’homme, il voit tous ses pas."
      }
    },
    {
      "verse": 22,
      "texts": {
        "BDS": "Car il n’y a pour lui aucune obscurité,\r\npas d’épaisses ténèbres où pourraient se cacher les artisans du mal.",
        "DBY": "Il n'y a pas de ténèbres, il n'y a pas d'ombre de la mort, où se puissent cacher les ouvriers d'iniquité.",
        "KJV": "[There is] no darkness, nor shadow of death, where the workers of iniquity may hide themselves.",
        "LSG": "Il n'y a ni ténèbres ni ombre de la mort, Où puissent se cacher ceux qui commettent l'iniquité.",
        "MAB": "Il n'y a ni ténèbres ni ombre de mort, où se puissent cacher les ouvriers d'iniquité.",
        "OST": "Il n'y a ni ténèbres ni ombre de la mort, où se puissent cacher les ouvriers d'iniquité.",
        "S21": "Il n'y a ni ténèbres ni ombre de la mort assez obscures pour cacher ceux qui commettent l’injustice."
      }
    },
    {
      "verse": 23,
      "texts": {
        "BDS": "Oui, Dieu n’a pas besoin d’épier longtemps un homme\r\npour le faire assigner devant lui en justice.",
        "DBY": "Car il ne pense pas longtemps à un homme pour le faire venir devant Dieu en jugement.",
        "KJV": "For he will not lay upon man more [than right]; that he should enter into judgment with God.",
        "LSG": "Dieu n'a pas besoin d'observer longtemps, Pour qu'un homme entre en jugement avec lui;",
        "MAB": "Mais il n'impute rien à l'homme contre la justice, lorsque l'homme vient à plaider avec le [Dieu] Fort.",
        "OST": "Il ne regarde pas à deux fois un homme, pour le faire aller en jugement avec lui.",
        "S21": "Dieu n'a pas besoin d'observer longtemps un homme pour le faire entrer en jugement avec lui."
      }
    },
    {
      "verse": 24,
      "texts": {
        "BDS": "Sans une longue enquête, il brise les tyrans\r\net met d’autres gens à leur place.",
        "DBY": "Il brise les puissants, sans examen, et il fait que d'autres se tiennent à leur place;",
        "KJV": "He shall break in pieces mighty men without number, and set others in their stead.",
        "LSG": "Il brise les grands sans information, Et il met d'autres à leur place;",
        "MAB": "Il brise, par des voies incompréhensibles, les hommes puissants, et il en établit d'autres en leur place.",
        "OST": "Il brise les puissants, sans enquête, et il en établit d'autres à leur place,",
        "S21": "Il brise les grands sans avoir à faire d’enquête et il les remplace par d’autres,"
      }
    },
    {
      "verse": 25,
      "texts": {
        "BDS": "Car il connaît leurs œuvres.\r\nAussi, en pleine nuit, soudain, il les renverse, et on les foule aux pieds.",
        "DBY": "En effet il connaît leurs œuvres: il les renverse de nuit, et ils sont écrasés.",
        "KJV": "Therefore he knoweth their works, and he overturneth [them] in the night, so that they are destroyed.",
        "LSG": "Car il connaît leurs oeuvres. Il les renverse de nuit, et ils sont écrasés;",
        "MAB": "Parce qu'il connaît leurs œuvres, il [les] renverse la nuit, et sont brisés.",
        "OST": "Parce qu'il connaît leurs œuvres; il les renverse de nuit, et ils sont brisés.",
        "S21": "car il connaît leur manière d’agir. En une nuit il les renverse et ils sont écrasés,"
      }
    },
    {
      "verse": 26,
      "texts": {
        "BDS": "Comme des criminels,\r\nil les frappe en public.",
        "DBY": "Il les frappe comme des méchants dans le lieu où ils sont en vue,",
        "KJV": "He striketh them as wicked men in the open sight of others;",
        "LSG": "Il les frappe comme des impies, A la face de tous les regards.",
        "MAB": "Parce qu'ils sont méchants, il les froisse à la vue de tout le monde.",
        "OST": "Il les flagelle comme des impies, à la vue de tout le monde,",
        "S21": "il les frappe comme des criminels, en public."
      }
    },
    {
      "verse": 27,
      "texts": {
        "BDS": "Ils lui tournaient le dos\r\net ignoraient toutes ses directives.",
        "DBY": "Parce qu'ils se sont retirés de lui, et qu'ils n'ont pas considéré toutes ses voies,",
        "KJV": "Because they turned back from him, and would not consider any of his ways:",
        "LSG": "En se détournant de lui, En abandonnant toutes ses voies,",
        "MAB": "A cause qu'ils se sont ainsi détournés de lui, et qu'ils n'ont considéré aucune de ses voies;",
        "OST": "Parce qu'ils se sont détournés de lui, et n'ont pas du tout pris garde à ses voies.",
        "S21": "C’est parce qu’ils se sont détournés de lui, parce qu’ils n’ont pas prêté attention à toutes ses voies."
      }
    },
    {
      "verse": 28,
      "texts": {
        "BDS": "Car ils ont fait monter vers lui le cri des pauvres\r\net il a entendu les cris des opprimés.",
        "DBY": "Pour faire monter vers lui le cri du pauvre, en sorte qu'il entende le cri des malheureux.",
        "KJV": "So that they cause the cry of the poor to come unto him, and he heareth the cry of the afflicted.",
        "LSG": "Ils ont fait monter à Dieu le cri du pauvre, Ils l'ont rendu attentif aux cris des malheureux.",
        "MAB": "En sorte qu'ils ont fait monter le cri du pauvre jusqu'à lui, et qu'il a entendu la clameur des affligés.",
        "OST": "Ils ont fait monter jusqu'à lui le cri du pauvre, et il a entendu la clameur des affligés.",
        "S21": "Ils ont fait monter vers lui le cri du faible, or il entend le cri des plus humbles."
      }
    },
    {
      "verse": 29,
      "texts": {
        "BDS": "S’il garde le silence, qui le condamnera?\r\nEt s’il cache sa face, qui pourra le voir malgré tout?\r\nOui, il en est ainsi pour les nations et pour les hommes,",
        "DBY": "Quand il donne la tranquillité, qui troublera? Il cache sa face, et qui le verra? Il fait ainsi, soit à une nation, soit à un homme,",
        "KJV": "When he giveth quietness, who then can make trouble? and when he hideth [his] face, who then can behold him? whether [it be done] against a nation, or against a man only:",
        "LSG": "S'il donne le repos, qui répandra le trouble? S'il cache sa face, qui pourra le voir? Il traite à l'égal soit une nation, soit un homme,",
        "MAB": "Que s'il donne du repos, qui est-ce qui causera du trouble? S'il cache sa face à quelqu'un, qui est-ce qui le regardera, soit qu'il s'agisse de toute une nation, ou qu'il ne s'agisse que d'un seul homme?",
        "OST": "S'il donne le repos, qui est-ce qui le condamnera? S'il cache sa face, qui le regardera? soit qu'il s'agisse d'un peuple ou d'un particulier,",
        "S21": "»S'il choisit la tranquillité, qui prononcera une condamnation? S'il cache son visage, qui pourra le voir? Il domine sur les nations aussi bien que sur les individus"
      }
    },
    {
      "verse": 30,
      "texts": {
        "BDS": "pour empêcher que règne un souverain injuste\r\net qu’on tende des pièges au peuple.",
        "DBY": "Pour empêcher l'homme impie de régner, pour écarter du peuple les pièges.",
        "KJV": "That the hypocrite reign not, lest the people be ensnared.",
        "LSG": "Afin que l'impie ne domine plus, Et qu'il ne soit plus un piège pour le peuple.",
        "MAB": "Afin que l'hypocrite ne règne point, de peur qu'il ne soit un filet pour le peuple.",
        "OST": "Pour que l'homme impie ne règne pas, pour qu'il ne soit pas en piège au peuple.",
        "S21": "pour empêcher l'homme impie de régner et d’être un piège pour le peuple."
      }
    },
    {
      "verse": 31,
      "texts": {
        "BDS": "Qu’un homme dise à Dieu:\r\n«J’ai eu mon châtiment, je ne me rendrai plus coupable.",
        "DBY": "Car a-t-il jamais dit à Dieu: Je porte ma peine, je ne ferai plus de mal;",
        "KJV": "Surely it is meet to be said unto God, I have borne [chastisement], I will not offend [any more]:",
        "LSG": "Car a-t-il jamais dit à Dieu: J'ai été châtié, je ne pécherai plus;",
        "MAB": "Certes, tu devrais avoir dit au [Dieu] Fort : J'ai souffert; mais je ne pécherai plus;",
        "OST": "Car a-t-il dit à Dieu: \"J'ai souffert, je ne pécherai plus;",
        "S21": "En effet, a-t-il déjà dit à Dieu: ‘J'ai supporté les conséquences de ma faute, je cesserai de faire le mal."
      }
    },
    {
      "verse": 32,
      "texts": {
        "BDS": "Ce que je n’ai pas vu, toi, fais-le-moi connaître.\r\nSi j’ai commis des fautes, je ne le ferai plus»?",
        "DBY": "Ce que je ne vois pas, montre-le-moi; si j'ai commis l'iniquité, je ne le referai pas?",
        "KJV": "[That which] I see not teach thou me: if I have done iniquity, I will do no more.",
        "LSG": "Montre-moi ce que je ne vois pas; Si j'ai commis des injustices, je n'en commettrai plus?",
        "MAB": "Et toi, [Seigneur!] enseigne-moi ce qui est au delà de ce que je vois; et si j'ai mal fait, je ne continuerai plus.",
        "OST": "Ce que je ne vois pas, montre-le-moi; si j'ai fait le mal, je ne le ferai plus? \"",
        "S21": "Montre-moi toi-même ce que je ne vois pas encore: si j'ai commis des injustices, je n'en commettrai plus’?"
      }
    },
    {
      "verse": 33,
      "texts": {
        "BDS": "Dieu devrait-il consulter ton avis pour juger un tel homme?\r\nQu’en dis-tu, toi, qui critiques ses voies? Puisque c’est toi qui prétends statuer et non pas moi,\r\ndis donc ce que tu sais!",
        "DBY": "Rétribuera-t-il selon tes pensées? car tu as rejeté son jugement, car toi, tu as choisi, et non pas moi; ce que tu sais, dis-le donc.",
        "KJV": "[Should it be] according to thy mind? he will recompense it, whether thou refuse, or whether thou choose; and not I: therefore speak what thou knowest.",
        "LSG": "Est-ce d'après toi que Dieu rendra la justice? C'est toi qui rejettes, qui choisis, mais non pas moi; Ce que tu sais, dis-le donc!",
        "MAB": "[Mais Dieu] ne te le rendra-t-il pas, puisque tu as rejeté son châtiment, quand tu as fait le choix que tu as fait? Pour moi, je ne [saurais que dire à cela]; mais toi, si tu as quelque chose à répondre, parle.",
        "OST": "Est-ce donc d'après tes idées que le mal doit être puni? Car tu as montré du mécontentement. Ainsi, c'est à toi de décider, non à moi! Dis ce que tu sais.",
        "S21": "»Est-ce d'après toi que Dieu rendra justice, alors que tu fais preuve de mépris? C’est à toi de choisir, pas à moi. Ce que tu sais, dis-le donc!"
      }
    },
    {
      "verse": 34,
      "texts": {
        "BDS": "Les hommes de bon sens aussi bien que les sages qui m’auront entendu\r\nconviendront avec moi:",
        "DBY": "Les hommes de sens me diront, et un homme sage qui m'écoute:",
        "KJV": "Let men of understanding tell me, and let a wise man hearken unto me.",
        "LSG": "Les hommes de sens seront de mon avis, Le sage qui m'écoute pensera comme moi.",
        "MAB": "Les gens de bon sens diront avec moi, et tout homme sage en conviendra,",
        "OST": "Les hommes de sens me diront, ainsi que le sage qui m'aura écouté:",
        "S21": "Les hommes de bon sens ainsi que les sages qui m'écoutent me diront:"
      }
    },
    {
      "verse": 35,
      "texts": {
        "BDS": "Job parle sans savoir\r\net ses paroles manquent d’intelligence.",
        "DBY": "Job n'a pas parlé avec connaissance, et ses paroles ne sont pas intelligentes;",
        "KJV": "Job hath spoken without knowledge, and his words [were] without wisdom.",
        "LSG": "Job parle sans intelligence, Et ses discours manquent de raison.",
        "MAB": "Que Job n'a pas parlé avec connaissance, et que ses paroles non point été avec intelligence.",
        "OST": "\"Job ne parle pas avec con-naissance, et ses paroles sont sans intelligence. \"",
        "S21": "‘Job parle sans rien savoir et ses paroles manquent de discernement."
      }
    },
    {
      "verse": 36,
      "texts": {
        "BDS": "Que son épreuve aille jusqu’à son terme\r\npuisqu’il répond à la manière des injustes.",
        "DBY": "Je voudrais que Job fût éprouvé jusqu'au bout, parce qu'il a répondu à la manière des hommes iniques;",
        "KJV": "My desire [is that] Job may be tried unto the end because of [his] answers for wicked men.",
        "LSG": "Qu'il continue donc à être éprouvé, Puisqu'il répond comme font les méchants!",
        "MAB": "Ha! mon père, que Job soit éprouvé jusqu'à ce qu'il soit vaincu, puisqu'il a répondu comme les impies.",
        "OST": "Ah! que Job soit éprouvé jusqu'à la fin, puisqu'il a répondu comme les méchants!",
        "S21": "Que Job soit donc mis à l’épreuve jusqu’au bout, puisqu'il répond comme le feraient des hommes adonnés au mal!"
      }
    },
    {
      "verse": 37,
      "texts": {
        "BDS": "Car, en plus de sa faute, voilà qu’il se révolte,\r\nil sème le doute parmi nous\r\net puis il multiplie ses propos contre Dieu.",
        "DBY": "Car il a ajouté à son péché la transgression; il bat des mains parmi nous, et multiplie ses paroles contre Dieu.",
        "KJV": "For he addeth rebellion unto his sin, he clappeth [his hands] among us, and multiplieth his words against God.",
        "LSG": "Car il ajoute à ses fautes de nouveaux péchés; Il bat des mains au milieu de nous, Il multiplie ses paroles contre Dieu.",
        "MAB": "Car [autrement] il ajoutera péché sur péché, il battra des mains entre nous, et parlera de plus en plus contre le [Dieu] Fort.",
        "OST": "Car il ajoute à son péché une transgression nouvelle; il s'applaudit au milieu de nous; il parle de plus en plus contre Dieu.",
        "S21": "En effet, il ajoute la révolte à son péché; il sème le doute au milieu de nous et il multiplie ses paroles contre Dieu.’»"
      }
    }
  ]
}