{
  "bookCode": "PSA",
  "chapter": 149,
  "verses": [
    {
      "verse": 1,
      "texts": {
        "BDS": "Célébrez l’Eternel!\r\nChantez pour l’Eternel un cantique nouveau!\r\nCélébrez ses louanges dans l’assemblée de ses fidèles!",
        "DBY": "Chantez à l'Éternel un cantique nouveau! Chantez sa louange dans la congrégation des saints.",
        "KJV": "Praise ye the LORD. Sing unto the LORD a new song, [and] his praise in the congregation of saints.",
        "LSG": "Louez l'Eternel! Chantez à l'Eternel un cantique nouveau! Chantez ses louanges dans l'assemblée des fidèles!",
        "MAB": "Louez l'Eternel. Chantez à l'Eternel un nouveau Cantique, [et] sa louange dans l'assemblée de ses bien-aimés.",
        "OST": "Louez l'Éternel! Chantez à l'Éternel un cantique nouveau, et sa louange dans l'assemblée de ses bien-aimés.",
        "S21": "Louez l’Eternel! Chantez en l’honneur de l’Eternel un cantique nouveau, chantez sa louange dans l’assemblée des fidèles!"
      }
    },
    {
      "verse": 2,
      "texts": {
        "BDS": "Exulte de joie, Israël: il est ton Créateur!\r\nQue les fils de Sion\r\néclatent d’allégresse à cause de leur roi!",
        "DBY": "Qu'Israël se réjouisse en celui qui l'a fait; que les fils de Sion s'égayent en leur roi!",
        "KJV": "Let Israel rejoice in him that made him: let the children of Zion be joyful in their King.",
        "LSG": "Qu'Israël se réjouisse en celui qui l'a créé! Que les fils de Sion soient dans l'allégresse à cause de leur roi!",
        "MAB": "Qu'Israël se réjouisse en celui qui l'a fait, [et] que les enfants de Sion s'égayent en leur Roi.",
        "OST": "Qu'Israël se réjouisse en celui qui l'a fait; que les enfants de Sion s'égaient en leur Roi!",
        "S21": "Qu’Israël se réjouisse en son créateur, que les habitants de Sion soient dans l’allégresse à cause de leur roi!"
      }
    },
    {
      "verse": 3,
      "texts": {
        "BDS": "Qu’ils le louent par des danses,\r\nqu’ils le célèbrent avec le tambourin et avec la cithare!",
        "DBY": "Qu'ils louent son nom avec des danses, qu'ils chantent ses louanges avec le tambourin et avec la harpe!",
        "KJV": "Let them praise his name in the dance: let them sing praises unto him with the timbrel and harp.",
        "LSG": "Qu'ils louent son nom avec des danses, Qu'ils le célèbrent avec le tambourin et la harpe!",
        "MAB": "Qu'ils louent son Nom sur la flûte, qu'ils lui psalmodient sur le tambour, et sur la harpe.",
        "OST": "Qu'ils louent son nom avec des danses, qu'ils le chantent avec le tambourin et la harpe!",
        "S21": "Qu’ils louent son nom avec des danses, qu’ils le célèbrent avec le tambourin et la harpe!"
      }
    },
    {
      "verse": 4,
      "texts": {
        "BDS": "Car l’Eternel prend plaisir en son peuple,\r\net il accorde aux humbles le salut pour parure.",
        "DBY": "Car l'Éternel prend plaisir en son peuple; il pare les débonnaires de salut.",
        "KJV": "For the LORD taketh pleasure in his people: he will beautify the meek with salvation.",
        "LSG": "Car l'Eternel prend plaisir à son peuple, Il glorifie les malheureux en les sauvant.",
        "MAB": "Car l'Eternel met son affection en son peuple; il rendra honorables les débonnaires en les délivrant.",
        "OST": "Car l'Éternel prend plaisir en son peuple; il glorifiera les humbles par son salut.",
        "S21": "En effet, l’Eternel prend plaisir en son peuple, il accorde aux humbles le salut pour parure."
      }
    },
    {
      "verse": 5,
      "texts": {
        "BDS": "Que ses fidèles exultent de fierté,\r\nqu’ils crient de joie quand ils sont sur leur couche,",
        "DBY": "Que les saints se réjouissent de la gloire, qu'ils exultent avec chant de triomphe sur leurs lits!",
        "KJV": "Let the saints be joyful in glory: let them sing aloud upon their beds.",
        "LSG": "Que les fidèles triomphent dans la gloire, Qu'ils poussent des cris de joie sur leur couche!",
        "MAB": "Les bien-aimés s'égayeront avec gloire, [et] ils se réjouiront dans leurs lits.",
        "OST": "Que ses bien-aimés triomphent avec gloire; qu'ils poussent des cris de joie sur leur couche!",
        "S21": "Que les fidèles exultent dans la gloire, qu’ils poussent des cris de joie sur leur lit!"
      }
    },
    {
      "verse": 6,
      "texts": {
        "BDS": "et qu’ils exaltent Dieu à pleine voix.\r\nQu’ils tiennent aussi dans leurs mains l’épée à deux tranchants",
        "DBY": "Les louanges de Dieu sont dans leur bouche, et une épée à deux tranchants dans leur main,",
        "KJV": "[Let] the high [praises] of God [be] in their mouth, and a twoedged sword in their hand;",
        "LSG": "Que les louanges de Dieu soient dans leur bouche, Et le glaive à deux tranchants dans leur main,",
        "MAB": "Les louanges du [Dieu] Fort seront dans leur bouche, et des épées affilées à deux tranchants dans leur main.",
        "OST": "Les louanges de Dieu sont dans leur bouche, et l'épée à deux tranchants dans leur main,",
        "S21": "Que les louanges de Dieu soient dans leur bouche, et l’épée à deux tranchants dans leur main!"
      }
    },
    {
      "verse": 7,
      "texts": {
        "BDS": "pour punir les nations\r\net pour châtier les peuples.",
        "DBY": "Pour exécuter la vengeance contre les nations, des châtiments au milieu des peuples;",
        "KJV": "To execute vengeance upon the heathen, [and] punishments upon the people;",
        "LSG": "Pour exercer la vengeance sur les nations, Pour châtier les peuples,",
        "MAB": "Pour se venger des nations, [et] pour châtier les peuples.",
        "OST": "Pour faire vengeance parmi les nations et pour châtier les peuples;",
        "S21": "Ainsi ils tireront vengeance des nations, ils puniront les peuples;"
      }
    },
    {
      "verse": 8,
      "texts": {
        "BDS": "Ils chargeront leurs rois de chaînes\r\net ils mettront aux fers leurs dignitaires",
        "DBY": "Pour lier leurs rois de chaînes, et leurs nobles de ceps de fer;",
        "KJV": "To bind their kings with chains, and their nobles with fetters of iron;",
        "LSG": "Pour lier leurs rois avec des chaînes Et leurs grands avec des ceps de fer,",
        "MAB": "Pour lier leurs Rois de chaînes, et les plus honorables d'entr'eux de ceps de fer;",
        "OST": "Pour lier leurs rois avec des chaînes, et leurs grands avec des ceps de fer;",
        "S21": "ils attacheront leurs rois avec des chaînes, et leurs grands avec des entraves en fer;"
      }
    },
    {
      "verse": 9,
      "texts": {
        "BDS": "pour accomplir sur eux le jugement prescrit.\r\nC’est l’honneur qui revient à chacun des fidèles.\r\nCélébrez l’Eternel!",
        "DBY": "Pour exécuter contre eux le jugement qui est écrit. Cette gloire est pour tous ses saints. Louez Jah!",
        "KJV": "To execute upon them the judgment written: this honour have all his saints. Praise ye the LORD.",
        "LSG": "Pour exécuter contre eux le jugement qui est écrit! C'est une gloire pour tous ses fidèles. Louez l'Eternel!",
        "MAB": "Pour exercer sur eux le jugement qui est écrit. Cet honneur est pour tous ses bien-aimés. Louez l'Eternel.",
        "OST": "Pour exercer sur eux le jugement qui est écrit. Cet honneur est pour tous ses bien-aimés. Louez l'Éternel!",
        "S21": "ils accompliront contre eux le jugement qui est écrit. Quel honneur pour tous ses fidèles! Louez l’Eternel!"
      }
    }
  ]
}